synthex/__init__.py
synthex/api_client.py
synthex/consts.py
synthex/credits_api.py
synthex/decorators.py
synthex/exceptions.py
synthex/jobs_api.py
synthex/users_api.py
synthex/models/__init__.py
synthex/models/credits.py
synthex/models/jobs.py
synthex/models/responses.py
synthex/models/users.py
synthex_python-0.1.1.dist-info/licenses/LICENSE
tests/__init__.py
tests/conftest.py
tests/integration/__init__.py
tests/integration/test_base.py
tests/integration/test_credits.py
tests/integration/test_jobs.py
tests/integration/test_users.py
tests/unit/__init__.py
tests/unit/test_base.py
tests/unit/test_credits.py
tests/unit/test_jobs.py
tests/unit/test_users.py
synthex_python-0.1.1.dist-info/METADATA
synthex_python-0.1.1.dist-info/WHEEL
synthex_python-0.1.1.dist-info/top_level.txt
synthex_python-0.1.1.dist-info/RECORD
