Metadata-Version: 2.4
Name: synthex-python
Version: 0.1.1
Summary: Synthex python library - developed by Tanaos
Author: Saurabh Pradhan
Author-email: Riccardo Lucato <riccardo@tanaos.com>
License: MIT
Project-URL: homepage, https://github.com/tanaos/synthex-python
Classifier: Development Status :: 3 - Alpha
Classifier: Intended Audience :: Developers
Classifier: License :: OSI Approved :: MIT License
Classifier: Programming Language :: Python :: 3
Classifier: Programming Language :: Python :: 3.9
Classifier: Programming Language :: Python :: 3.10
Classifier: Topic :: Software Development :: Libraries :: Python Modules
Classifier: Operating System :: OS Independent
Requires-Python: >=3.7
License-File: LICENSE
Requires-Dist: requests>=2.32.3
Requires-Dist: responses>=0.25.7
Requires-Dist: python-dotenv>=1.1.0
Requires-Dist: pydantic>=2.11.2
Dynamic: license-file
